ckanext_oidc_pkce-0.4.1-py3.12-nspkg.pth
ckanext/oidc_pkce/__init__.py
ckanext/oidc_pkce/config.py
ckanext/oidc_pkce/config_declaration.yaml
ckanext/oidc_pkce/helpers.py
ckanext/oidc_pkce/interfaces.py
ckanext/oidc_pkce/plugin.py
ckanext/oidc_pkce/signals.py
ckanext/oidc_pkce/utils.py
ckanext/oidc_pkce/views.py
ckanext/oidc_pkce/templates/user/login.html
ckanext/oidc_pkce/tests/__init__.py
ckanext/oidc_pkce/tests/conftest.py
ckanext/oidc_pkce/tests/test_plugin.py
ckanext/oidc_pkce/tests/test_utils.py
ckanext_oidc_pkce-0.4.1.dist-info/licenses/LICENSE
ckanext_oidc_pkce-0.4.1.dist-info/METADATA
ckanext_oidc_pkce-0.4.1.dist-info/WHEEL
ckanext_oidc_pkce-0.4.1.dist-info/entry_points.txt
ckanext_oidc_pkce-0.4.1.dist-info/namespace_packages.txt
ckanext_oidc_pkce-0.4.1.dist-info/top_level.txt
ckanext_oidc_pkce-0.4.1.dist-info/RECORD
